{"ab":"abhaasi","ada":"adangme","ady":"ad\u00f5gee","aa":"afari","afh":"afrihili","af":"afrikaani","agq":"aghemi","ay":"aimara","ain":"ainu","akk":"akadi","ak":"akani","ach":"akoli","bss":"akoose","akz":"Alabama","nds":"alamsaksa","dsb":"alamsorbi","sq":"albaania","ale":"aleuudi","arq":"Algerian Arabic","alt":"altai","kj":"ambo","ase":"American Sign Language","am":"amhari","anp":"angika","njo":"Ao Naga","ar":"araabia","ar_001":"araabia (t\u00e4nap\u00e4evane)","an":"aragoni","arc":"aramea","aro":"Araona","arp":"arapaho","arn":"araukaani","arw":"aravaki","hy":"armeenia","rup":"aromuuni","frp":"Arpitan","asa":"asa","az":"aserbaid\u017eaani","as":"assami","ast":"astuuria","cch":"atsami","ace":"at\u0161ehi","en_AU":"Australian English","de_AT":"Austrian German","av":"avaari","awa":"avadhi","ae":"avesta","bfq":"Badaga","ksf":"bafia","bfd":"bafuti","bqi":"Bakhtiari","ban":"bali","bm":"bambara","bax":"bamuni","bjn":"Banjar","bas":"basa","eu":"baski","ba":"ba\u0161kiiri","bbc":"Batak Toba","bar":"Bavarian","bej":"bed\u017ea","pau":"belau","bal":"belut\u0161i","bem":"bemba","bez":"bena","bn":"bengali","bew":"Betawi","bho":"bhod\u017epuri","bik":"bikoli","byn":"bilini","my":"birma","bpy":"Bishnupriya","bi":"bislama","zbl":"bliss\u00fcmbolid","brx":"bodo","bs":"bosnia","bra":"brad\u017ei","brh":"Brahui","pt_BR":"Brazilian Portuguese","br":"bretooni","bug":"bugi","bg":"bulgaaria","bum":"bulu","bua":"burjaadi","frc":"Cajun French","en_CA":"Canadian English","fr_CA":"Canadian French","cps":"Capiznon","cay":"cayuga","dtp":"Central Dusun","esu":"Central Yupik","cgg":"chiga","qug":"Chimborazo Highland Quichua","ksh":"cologniani","dar":"dargi","dzg":"dazaga","del":"delavari","din":"dinka","dyu":"djula","doi":"dogri","dgr":"dogribi","dz":"dzongkha","dua":"duala","bin":"edo","elx":"eelami","et":"eesti","efi":"efiki","arz":"Egyptian Arabic","eka":"ekad\u017euki","ebu":"embu","egl":"Emilian","myv":"ersa","eo":"esperanto","gez":"etioopia","ee":"eve","ewo":"evondo","ext":"Extremaduran","fan":"fangi","fat":"fanti","fj":"fid\u017ei","hif":"Fiji Hindi","fil":"filipino","nl_BE":"flaami","phn":"foiniikia","fon":"foni","gur":"Frafra","fur":"friuuli","ff":"fulbe","fo":"f\u00e4\u00e4ri","gaa":"gaa","gd":"gaeli","gag":"gagauusi","gay":"gajo","gl":"galeegi","gan":"Gan Chinese","lg":"ganda","gba":"gbaja","aln":"Gheg Albanian","bbj":"ghomala","glk":"Gilaki","gom":"Goan Konkani","gon":"gondi","got":"gooti","gor":"gorontalo","grb":"grebo","ka":"gruusia","kl":"gr\u00f6\u00f6ni","gn":"guaranii","gu":"gud\u017earati","guz":"gusii","gwi":"gvit\u0161ini","hai":"haida","ht":"haiti","hak":"Hakka Chinese","ha":"hausa","haw":"havai","he":"heebrea","hz":"herero","hit":"heti","zh":"hiina","zh_Hans":"hiina (lihtsustatud)","zh_Hant":"hiina (traditsiooniline)","hil":"hiligainoni","hi":"hindi","es":"hispaania","es_ES":"hispaania (Euroopa)","hmn":"hmongi","nl":"hollandi","hr":"horvaadi","hup":"hupa","iba":"ibani","ibb":"ibibio","ig":"ibo","frs":"idafriisi","io":"ido","ga":"iiri","ilo":"iloko","smn":"inari saami","id":"indoneesia","en":"inglise","en_GB":"inglise (Briti)","en_US":"inglise (USA)","izh":"Ingrian","inh":"ingu\u0161i","ik":"injupiaki","ia":"interlingua","ie":"interlingue","iu":"inuktituti","is":"islandi","it":"itaalia","bkm":"ita\u014bikomi","ja":"jaapani","jv":"jaava","sah":"jakuudi","jam":"Jamaican Creole English","yao":"jao","yap":"japi","yi":"jidi\u0161i","kaj":"jju","dyo":"jola-fonyi","yo":"joruba","jut":"Jutish","jrb":"juudiaraabia","jpr":"juudip\u00e4rsia","quc":"k\u2019iche\u2019","kaw":"kaavi","kbd":"kabardi-t\u0161erkessi","kab":"kabiili","kea":"kabuverdianu","cad":"kado","kgp":"Kaingang","kkj":"kako","kln":"kaljenjin","xal":"kalm\u00f5ki","kam":"kamba","kbl":"kanembu","kn":"kannada","yue":"kantoni","kr":"kanuri","kaa":"karakalpaki","krc":"karat\u0161ai-balkaari","car":"kariibi","krl":"karjala","kk":"kasahhi","ks":"ka\u0161miiri","csb":"ka\u0161uubi","ca":"katalaani","kac":"kat\u0161ini","ken":"Kenyang","tzm":"Kesk-Maroko tamazighti","dum":"keskhollandi","mga":"keskiiri","enm":"keskinglise","frm":"keskprantsuse","gmh":"kesk\u00fclemsaksa","qu":"ket\u0161ua","kha":"khasi","km":"khmeeri","khw":"Khowar","ki":"kikuju","krj":"Kinaray-a","ky":"kirgiisi","gil":"kiribati","cu":"kirikuslaavi","kiu":"Kirmanjki","syc":"klassikaline s\u00fc\u00fcria","tlh":"klingoni","sms":"koltasaami","kv":"komi","swb":"komoori","kg":"kongo","swc":"Kongo suahiili","kok":"konkani","xh":"koosa","cop":"kopti","ko":"korea","kw":"korni","kfo":"koro","co":"korsika","kos":"kosrae","avk":"Kotava","khq":"koyra chiini","ses":"koyraboro senni","kpe":"kpelle","el":"kreeka","cr":"krii","crh":"krimmitatari","kri":"Krio","kum":"kum\u00f5ki","ku":"kurdi","kut":"kutenai","nmg":"kwasio","cy":"k\u00f5mri","lad":"ladiino","la":"ladina","lah":"lahnda","lkt":"lakota","lam":"lamba","lag":"langi","lo":"lao","lzz":"Laz","ltg":"Latgalian","es_419":"Latin American Spanish","lt":"leedu","lez":"lesgi","lb":"letseburgi","lij":"Ligurian","li":"limburgi","ln":"lingala","lfn":"Lingua Franca Nova","lzh":"Literary Chinese","liv":"Livonian","jbo":"lojbani","lmo":"Lombard","loz":"lozi","sli":"Lower Silesian","lu":"luba","lua":"luba-lulua","lui":"luisenjo","smj":"lule saami","lun":"lunda","luo":"luo","lus":"lu\u0161ei","luy":"luyia","nr":"l\u00f5unandebele","sma":"l\u00f5unasaami","st":"l\u00f5unasotho","lv":"l\u00e4ti","fy":"l\u00e4\u00e4nefriisi","mde":"maba","jmc":"machame","mad":"madura","maf":"mafa","mag":"magali","vmf":"Main-Franconian","mai":"maithili","mak":"makassari","mk":"makedoonia","mgh":"makhuwa-meetto","kde":"makonde","mg":"malagassi","ms":"malai","ml":"malajalami","dv":"maldiivi","man":"malinke","mt":"malta","mdr":"mandari","mnc":"mand\u017eu","mni":"manipuri","mi":"maoori","mr":"marathi","chm":"mari","mh":"mar\u0161alli","mwr":"marvari","mas":"masai","mus":"maskogi","mzn":"Mazanderani","mfe":"Mauritiuse kreoolkeel","kmb":"mbundu","byv":"medumba","men":"mende","mwv":"Mentawai","mer":"meru","mgo":"meta\u2019","es_MX":"Mexican Spanish","mic":"mikmaki","nan":"Min Nan Chinese","min":"minangkabau","xmf":"Mingrelian","mwl":"miranda","zxx":"mittekeeleline","mul":"mitu keelt","moh":"mohoogi","mdf":"mok\u0161a","ro_MD":"moldova","lol":"mongo","mn":"mongoli","mos":"more","ary":"Moroccan Arabic","ho":"motu","egy":"muinasegiptuse","mua":"mundangi","ttt":"Muslim Tat","rom":"mustlaskeel","gv":"m\u00e4nksi","und":"m\u00e4\u00e4ramata","mye":"myene","naq":"nama","nap":"napoli","na":"nauru","nv":"navaho","ng":"ndonga","ne":"nepali","new":"nevari","sba":"ngembay","nnh":"ngiembooni","jgo":"ngomba","yrl":"Nheengatu","nia":"niasi","niu":"niue","nym":"njamvesi","ny":"njand\u017ea","nyo":"njoro","nyn":"nkole","nqo":"nkoo","nog":"nogai","no":"norra","nb":"norra bokm\u00e5l","nn":"norra nynorsk","nov":"Novial","nzi":"nzima","nus":"nueri","oj":"od\u017eibvei","kru":"oraoni","or":"oria","om":"oromo","osa":"oseid\u017ei","ota":"osmanit\u00fcrgi","os":"osseedi","pi":"paali","pal":"pahlavi","pfl":"Palatine German","pam":"pampanga","pa":"pand\u017eabi","pag":"pangasinani","pap":"papiamento","nso":"pedi","pdc":"Pennsylvania German","koi":"permikomi","pcd":"Picard","pms":"Piedmontese","pdt":"Plautdietsch","pnt":"Pontic","pl":"poola","pon":"poonpei","pt":"portugali","pt_PT":"portugali (Euroopa)","fr":"prantsuse","oc":"provansi","prg":"Prussian","ps":"pu\u0161tu","frr":"p\u00f5hjafriisi","nd":"p\u00f5hjandebele","se":"p\u00f5hjasaami","fa":"p\u00e4rsia","raj":"rad\u017eastani","rap":"rapanui","rar":"rarotonga","rm":"retoromaani","rif":"Riffian","rgn":"Romagnol","rof":"rombo","root":"root","sv":"rootsi","rtm":"Rotuman","rug":"Roviana","rw":"ruanda","ro":"rumeenia","rn":"rundi","rue":"Rusyn","rwk":"rwa","ssy":"saho","kho":"saki","de":"saksa","de_CH":"saksa (k\u00f5rgsaksa)","sam":"samaaria aramea","saq":"samburu","sm":"samoa","sgs":"Samogitian","sad":"sandave","sg":"sango","sbp":"sangu","sa":"sanskriti","sat":"santali","zap":"sapoteegi","sc":"sardiinia","sas":"sasaki","sdc":"Sassarese Sardinian","stq":"Saterland Frisian","saz":"Saurashtra","ceb":"sebu","sly":"Selayar","seh":"sena","see":"seneca","sr":"serbia","sh":"serbia-horvaadi","srr":"sereri","sei":"Seri","ksb":"shambala","ii":"sichuani jii","sid":"sidamo","bla":"siksika","szl":"Silesian","sd":"sindhi","si":"singali","scn":"sitsiilia","dak":"siuu","den":"sleivi","sk":"slovaki","sl":"sloveeni","xog":"soga","sog":"sogdi","so":"somaali","snk":"soninke","fi":"soome","ckb":"sorani kurdi","azb":"South Azerbaijani","srn":"sranani","sw":"suahiili","suk":"sukuma","sux":"sumeri","su":"sunda","zun":"sunji","sus":"susu","zu":"suulu","ss":"svaasi","fr_CH":"Swiss French","sel":"s\u00f6lkupi","syr":"s\u00fc\u00fcria","chy":"\u0161aieeni","shn":"\u0161ani","sn":"\u0161ona","sco":"\u0161oti","gsw":"\u0161veitsisaksa","dje":"zarma","zza":"zaza","zea":"Zeelandic","zen":"zenaga","gbz":"Zoroastrian Dari","da":"taani","shi":"tachelhiti","tg":"tad\u017eiki","tl":"tagalogi","ty":"tahiti","th":"tai","dav":"taita","tly":"Talysh","zgh":"tamasikti (Maroko)","tmh":"tama\u0161eki","ta":"tamili","trv":"taroko","twq":"taswaqi","tt":"tatari","te":"telugu","tem":"temne","ter":"tereno","teo":"teso","tet":"tetumi","tig":"tigree","ti":"tigrinja","bo":"tiibeti","tiv":"tivi","tli":"tlingiti","tkl":"tokelau","to":"tonga","fit":"Tornedalen Finnish","tkr":"Tsakhur","tsd":"Tsakonian","ts":"tsonga","tn":"tsvana","shu":"T\u0161aadi araabia","chg":"t\u0161agatai","ch":"t\u0161amorro","cs":"t\u0161ehhi","chr":"t\u0161erokii","ce":"t\u0161et\u0161eeni","chb":"t\u0161ibt\u0161a","tsi":"t\u0161im\u0161i","chn":"t\u0161inuki \u017eargoon","chp":"t\u0161ipevai","tog":"t\u0161itonga","cho":"t\u0161okto","za":"t\u0161uangi","chk":"t\u0161uugi","cv":"t\u0161uva\u0161i","tcy":"Tulu","tum":"tumbuka","aeb":"Tunisian Arabic","tru":"Turoyo","tvl":"tuvalu","tw":"tvii","tyv":"t\u00f5va","tr":"t\u00fcrgi","tk":"t\u00fcrkmeeni","kcg":"tyapi","udm":"udmurdi","uga":"ugariti","ug":"uiguuri","uk":"ukraina","umb":"umbundu","hu":"ungari","ur":"urdu","uz":"usbeki","tpi":"uusmelaneesia","vot":"vadja","vai":"vai","be":"valgevene","wa":"vallooni","sga":"vanaiiri","ang":"vanainglise","grc":"vanakreeka","nwc":"vananevari","fro":"vanaprantsuse","pro":"vanaprovansi","non":"vanap\u00f5hjala","peo":"vanap\u00e4rsia","goh":"vana\u00fclemsaksa","war":"varai","was":"va\u0161o","ve":"venda","ru":"vene","vec":"Venetian","vep":"Veps","vi":"vietnami","wal":"volamo","vo":"volap\u00fcki","wo":"volofi","vun":"vunjo","vro":"V\u00f5ro","wae":"walseri","wbp":"Warlpiri","guc":"Wayuu","vls":"West Flemish","mrj":"Western Mari","wuu":"Wu Chinese","hsb":"\u00fclemsorbi","hsn":"Xiang Chinese","yav":"yangbeni","ybb":"yemba"}